RealHand/__init__.py
RealHand/real_hand_api.py
RealHand/config/__init__.py
RealHand/core/__init__.py
RealHand/core/can/__init__.py
RealHand/core/can/real_hand_g20_can.py
RealHand/core/can/real_hand_l10_can.py
RealHand/core/can/real_hand_l20_can.py
RealHand/core/can/real_hand_l21_can.py
RealHand/core/can/real_hand_l24_can.py
RealHand/core/can/real_hand_l25_can.py
RealHand/core/can/real_hand_l7_can.py
RealHand/core/can/real_hand_o6_can.py
RealHand/core/rs485/real_hand_l10_rs485.py
RealHand/core/rs485/real_hand_l6_rs485.py
RealHand/core/rs485/real_hand_o6_rs485.py
RealHand/utils/__init__.py
RealHand/utils/color_msg.py
RealHand/utils/init_real_hand.py
RealHand/utils/load_write_yaml.py
RealHand/utils/mapping.py
RealHand/utils/open_can.py
realhand_python_sdk-0.1.0.dist-info/METADATA
realhand_python_sdk-0.1.0.dist-info/WHEEL
realhand_python_sdk-0.1.0.dist-info/top_level.txt
realhand_python_sdk-0.1.0.dist-info/RECORD
