Metadata-Version: 2.4
Name: realhand-python-sdk
Version: 0.1.0
Author-email: RealHand <support@realhand.com>
License: MIT
Requires-Python: >=3.8
